[
  {
    "subject": "algorithms",
    "question": "Что в первую очередь определяет тип данных переменной в C/C++?",
    "options": {
      "A": "Допустимый набор значений",
      "B": "Набор разрешённых операций",
      "C": "Способ интерпретации битов в памяти",
      "D": "Обязательное имя переменной",
      "E": "Точное место переменной в оперативной памяти"
    },
    "correctAnswers": [
      "A",
      "B",
      "C"
    ],
    "explanation": "Тип данных определяет диапазон значений, допустимые операции и способ интерпретации двоичного представления. Имя и конкретный адрес памяти типом не определяются.",
    "author": "Рабат",
    "topic": "День 2 — Типы данных в C/C++"
  },
  {
    "subject": "algorithms",
    "question": "Какие из перечисленных типов относятся к целочисленным типам C++?",
    "options": {
      "A": "char",
      "B": "short",
      "C": "int",
      "D": "long long",
      "E": "double"
    },
    "correctAnswers": [
      "A",
      "B",
      "C",
      "D"
    ],
    "explanation": "char, short, int и long long относятся к целочисленным типам. double является вещественным типом.",
    "author": "Рабат",
    "topic": "День 2 — Типы данных в C/C++"
  },
  {
    "subject": "algorithms",
    "question": "Какое утверждение о sizeof(char) является правильным?",
    "options": {
      "A": "Всегда равно 1",
      "B": "Всегда равно 8",
      "C": "Зависит от разрядности процессора",
      "D": "Всегда равно sizeof(int)",
      "E": "Не определено стандартом"
    },
    "correctAnswers": [
      "A"
    ],
    "explanation": "Стандарт гарантирует, что sizeof(char) равно 1. Это означает один байт данной платформы, а не обязательно числовое значение 8 бит, хотя обычно байт содержит 8 бит.",
    "author": "Рабат",
    "topic": "День 2 — Типы данных в C/C++"
  },
  {
    "subject": "algorithms",
    "question": "Какое соотношение размеров целочисленных типов гарантируется стандартом C++?",
    "options": {
      "A": "sizeof(char) <= sizeof(short) <= sizeof(int) <= sizeof(long) <= sizeof(long long)",
      "B": "sizeof(char) < sizeof(short) < sizeof(int) < sizeof(long) < sizeof(long long)",
      "C": "sizeof(int) всегда равно sizeof(long)",
      "D": "sizeof(long) всегда равно 8",
      "E": "sizeof(short) всегда равно 2"
    },
    "correctAnswers": [
      "A"
    ],
    "explanation": "Стандарт гарантирует неубывающий порядок размеров. Равенство между некоторыми типами допускается, а конкретные размеры зависят от реализации.",
    "author": "Рабат",
    "topic": "День 2 — Типы данных в C/C++"
  },
  {
    "subject": "algorithms",
    "question": "Как вычисляется диапазон n-битного беззнакового целого типа?",
    "options": {
      "A": "От 0 до 2^n - 1",
      "B": "От -2^(n-1) до 2^(n-1) - 1",
      "C": "От 1 до 2^n",
      "D": "От -2^n до 2^n",
      "E": "От 0 до 2^(n-1)"
    },
    "correctAnswers": [
      "A"
    ],
    "explanation": "Беззнаковый тип использует все n битов для значения, поэтому содержит 2^n различных значений: от 0 до 2^n - 1.",
    "author": "Рабат",
    "topic": "День 2 — Типы данных в C/C++"
  },
  {
    "subject": "algorithms",
    "question": "Как вычисляется типичный диапазон n-битного знакового целого типа?",
    "options": {
      "A": "От -2^(n-1) до 2^(n-1) - 1",
      "B": "От 0 до 2^n - 1",
      "C": "От -2^n до 2^n - 1",
      "D": "От -2^(n-1) + 1 до 2^(n-1)",
      "E": "От 0 до 2^(n-1) - 1"
    },
    "correctAnswers": [
      "A"
    ],
    "explanation": "В современном представлении со знаком диапазон n-битного типа составляет от -2^(n-1) до 2^(n-1)-1.",
    "author": "Рабат",
    "topic": "День 2 — Типы данных в C/C++"
  },
  {
    "subject": "algorithms",
    "question": "Какие записи объявляют переменную типа signed int?",
    "options": {
      "A": "int x;",
      "B": "signed x;",
      "C": "signed int x;",
      "D": "unsigned x;",
      "E": "short x;"
    },
    "correctAnswers": [
      "A",
      "B",
      "C"
    ],
    "explanation": "int, signed и signed int обозначают один и тот же тип signed int. unsigned и short являются другими типами.",
    "author": "Рабат",
    "topic": "День 2 — Типы данных в C/C++"
  },
  {
    "subject": "algorithms",
    "question": "Какие утверждения об обычном char верны?",
    "options": {
      "A": "char является отдельным типом от signed char",
      "B": "char является отдельным типом от unsigned char",
      "C": "Знаковость обычного char зависит от реализации",
      "D": "char всегда является unsigned",
      "E": "char нельзя использовать в арифметических выражениях"
    },
    "correctAnswers": [
      "A",
      "B",
      "C"
    ],
    "explanation": "char, signed char и unsigned char — три различных типа. Обычный char может быть знаковым или беззнаковым в зависимости от платформы и настроек компилятора.",
    "author": "Рабат",
    "topic": "День 2 — Типы данных в C/C++"
  },
  {
    "subject": "algorithms",
    "question": "Какой результат обычно выведет программа на ASCII-совместимой системе?\n\nchar c = 'A';\nstd::cout << static_cast<int>(c);",
    "options": {
      "A": "65",
      "B": "A",
      "C": "1",
      "D": "97",
      "E": "Ошибка компиляции"
    },
    "correctAnswers": [
      "A"
    ],
    "explanation": "Символ 'A' имеет код 65 в ASCII. static_cast<int> преобразует символьный код в целое число.",
    "author": "Рабат",
    "topic": "День 2 — Типы данных в C/C++"
  },
  {
    "subject": "algorithms",
    "question": "Что произойдёт в следующем коде?\n\nchar c = 'A';\nc = c + 1;\nstd::cout << c;",
    "options": {
      "A": "Обычно будет выведено B",
      "B": "Будет выведено 66",
      "C": "Возникнет ошибка компиляции",
      "D": "Будет выведено A1",
      "E": "Результат всегда равен C"
    },
    "correctAnswers": [
      "A"
    ],
    "explanation": "char участвует в арифметике как целочисленный тип. Код символа увеличивается на единицу, после чего результат преобразуется обратно в char.",
    "author": "Рабат",
    "topic": "День 2 — Типы данных в C/C++"
  },
  {
    "subject": "algorithms",
    "question": "Какой тип имеет вещественный литерал 3.14 без суффикса?",
    "options": {
      "A": "double",
      "B": "float",
      "C": "long double",
      "D": "int",
      "E": "Тип выбирается по переменной слева"
    },
    "correctAnswers": [
      "A"
    ],
    "explanation": "Вещественный литерал без суффикса имеет тип double независимо от типа переменной, в которую затем будет записан.",
    "author": "Рабат",
    "topic": "День 2 — Типы данных в C/C++"
  },
  {
    "subject": "algorithms",
    "question": "Какой тип имеет литерал 3.14f?",
    "options": {
      "A": "float",
      "B": "double",
      "C": "long double",
      "D": "unsigned float",
      "E": "Тип определяется автоматически во время выполнения"
    },
    "correctAnswers": [
      "A"
    ],
    "explanation": "Суффикс f или F указывает, что вещественный литерал имеет тип float.",
    "author": "Рабат",
    "topic": "День 2 — Типы данных в C/C++"
  },
  {
    "subject": "algorithms",
    "question": "Какой тип имеет литерал 3.14L?",
    "options": {
      "A": "long double",
      "B": "long",
      "C": "double",
      "D": "float",
      "E": "long long"
    },
    "correctAnswers": [
      "A"
    ],
    "explanation": "Суффикс L у вещественного литерала обозначает тип long double.",
    "author": "Рабат",
    "topic": "День 2 — Типы данных в C/C++"
  },
  {
    "subject": "algorithms",
    "question": "Какова приблизительная точность стандартного float на большинстве современных систем?",
    "options": {
      "A": "6–7 значащих десятичных цифр",
      "B": "15–16 значащих десятичных цифр",
      "C": "Одна десятичная цифра",
      "D": "Все целые числа до 10^38 представляются точно",
      "E": "Точность всегда совпадает с double"
    },
    "correctAnswers": [
      "A"
    ],
    "explanation": "Типичный 32-битный float имеет около 24 значащих двоичных битов, что соответствует примерно 6–7 значащим десятичным цифрам.",
    "author": "Рабат",
    "topic": "День 2 — Типы данных в C/C++"
  },
  {
    "subject": "algorithms",
    "question": "Почему выражение 0.1 + 0.2 == 0.3 может вернуть false?",
    "options": {
      "A": "Многие десятичные дроби нельзя точно представить в двоичной системе",
      "B": "Оператор == не работает с double",
      "C": "double хранит только целые числа",
      "D": "0.1 автоматически преобразуется в int",
      "E": "Компилятор всегда округляет результат вверх"
    },
    "correctAnswers": [
      "A"
    ],
    "explanation": "0.1, 0.2 и 0.3 обычно представлены приближённо. Ошибки представления могут привести к тому, что вычисленный результат немного отличается от литерала 0.3.",
    "author": "Рабат",
    "topic": "День 2 — Типы данных в C/C++"
  },
  {
    "subject": "algorithms",
    "question": "Как корректнее сравнивать два вычисленных значения типа double?",
    "options": {
      "A": "Проверять, что абсолютная разность меньше допустимой погрешности",
      "B": "Всегда использовать оператор ==",
      "C": "Сначала привести оба числа к char",
      "D": "Сравнивать только их адреса",
      "E": "Преобразовать оба числа в bool"
    },
    "correctAnswers": [
      "A"
    ],
    "explanation": "Для результатов вычислений обычно применяют сравнение с погрешностью: abs(a - b) < epsilon. Размер epsilon выбирают с учётом масштаба задачи.",
    "author": "Рабат",
    "topic": "День 2 — Типы данных в C/C++"
  },
  {
    "subject": "algorithms",
    "question": "Какие значения преобразуются в false при преобразовании к bool?",
    "options": {
      "A": "Целое число 0",
      "B": "Вещественное число 0.0",
      "C": "Нулевой указатель",
      "D": "Число -1",
      "E": "Число 100"
    },
    "correctAnswers": [
      "A",
      "B",
      "C"
    ],
    "explanation": "Нулевые числовые значения и нулевой указатель преобразуются в false. Любое ненулевое числовое значение, включая отрицательное, преобразуется в true.",
    "author": "Рабат",
    "topic": "День 2 — Типы данных в C/C++"
  },
  {
    "subject": "algorithms",
    "question": "Какой результат выведет код?\n\nbool a = -10;\nbool b = 0;\nstd::cout << a << \" \" << b;",
    "options": {
      "A": "1 0",
      "B": "0 0",
      "C": "-10 0",
      "D": "true false независимо от настроек потока",
      "E": "Ошибка компиляции"
    },
    "correctAnswers": [
      "A"
    ],
    "explanation": "Любое ненулевое число преобразуется в true, а ноль — в false. По умолчанию cout выводит bool как 1 и 0.",
    "author": "Рабат",
    "topic": "День 2 — Типы данных в C/C++"
  },
  {
    "subject": "algorithms",
    "question": "Для чего применяется тип void?",
    "options": {
      "A": "Для обозначения отсутствия возвращаемого значения функции",
      "B": "Для универсального указателя void*",
      "C": "Для создания обычных переменных без значения",
      "D": "Для хранения только нуля",
      "E": "Для автоматического определения типа"
    },
    "correctAnswers": [
      "A",
      "B"
    ],
    "explanation": "void используется как возвращаемый тип функций, которые ничего не возвращают, а void* может хранить адрес объекта произвольного типа. Обычную переменную типа void создать нельзя.",
    "author": "Рабат",
    "topic": "День 2 — Типы данных в C/C++"
  },
  {
    "subject": "algorithms",
    "question": "Почему нельзя напрямую разыменовать указатель типа void*?",
    "options": {
      "A": "Компилятор не знает размер и конкретный тип объекта",
      "B": "void* всегда равен nullptr",
      "C": "void* хранится только в регистрах",
      "D": "void* не может содержать адрес",
      "E": "Разыменование разрешено только для char*"
    },
    "correctAnswers": [
      "A"
    ],
    "explanation": "Для разыменования компилятору необходимо знать тип объекта и размер данных. Поэтому void* сначала приводят к указателю конкретного типа.",
    "author": "Рабат",
    "topic": "День 2 — Типы данных в C/C++"
  },
  {
    "subject": "algorithms",
    "question": "Какой результат получит переменная result?\n\nint a = 5;\nint b = 2;\ndouble result = a / b;",
    "options": {
      "A": "2.0",
      "B": "2.5",
      "C": "3.0",
      "D": "Ошибка компиляции",
      "E": "Результат зависит от размера double"
    },
    "correctAnswers": [
      "A"
    ],
    "explanation": "Оба операнда имеют тип int, поэтому сначала выполняется целочисленное деление 5 / 2 = 2. После этого число 2 преобразуется в double.",
    "author": "Рабат",
    "topic": "День 2 — Типы данных в C/C++"
  },
  {
    "subject": "algorithms",
    "question": "Какие выражения дадут результат 2.5?",
    "options": {
      "A": "5.0 / 2",
      "B": "5 / 2.0",
      "C": "static_cast<double>(5) / 2",
      "D": "static_cast<double>(5 / 2)",
      "E": "double result = 5 / 2"
    },
    "correctAnswers": [
      "A",
      "B",
      "C"
    ],
    "explanation": "В вариантах A, B и C один операнд становится вещественным до деления. В D и E сначала выполняется целочисленное деление, результатом которого является 2.",
    "author": "Рабат",
    "topic": "День 2 — Типы данных в C/C++"
  },
  {
    "subject": "algorithms",
    "question": "Какой результат даст код?\n\ndouble x = -3.9;\nint y = static_cast<int>(x);",
    "options": {
      "A": "-3",
      "B": "-4",
      "C": "3",
      "D": "0",
      "E": "Ошибка компиляции"
    },
    "correctAnswers": [
      "A"
    ],
    "explanation": "При преобразовании вещественного значения в целое дробная часть отбрасывается по направлению к нулю. Поэтому -3.9 превращается в -3.",
    "author": "Рабат",
    "topic": "День 2 — Типы данных в C/C++"
  },
  {
    "subject": "algorithms",
    "question": "Какое преобразование является сужающим?",
    "options": {
      "A": "double в int",
      "B": "long long в short",
      "C": "double в float",
      "D": "short в int",
      "E": "float в double"
    },
    "correctAnswers": [
      "A",
      "B",
      "C"
    ],
    "explanation": "Сужающее преобразование может уменьшить диапазон или точность. short в int и float в double обычно являются расширяющими преобразованиями.",
    "author": "Рабат",
    "topic": "День 2 — Типы данных в C/C++"
  },
  {
    "subject": "algorithms",
    "question": "Что произойдёт при компиляции следующего кода C++?\n\nint x{3.14};",
    "options": {
      "A": "Ошибка компиляции из-за сужающего преобразования",
      "B": "x станет равен 3",
      "C": "x станет равен 4",
      "D": "x получит тип double",
      "E": "Поведение не определено"
    },
    "correctAnswers": [
      "A"
    ],
    "explanation": "Списковая инициализация с фигурными скобками запрещает сужающее преобразование из double в int.",
    "author": "Рабат",
    "topic": "День 2 — Типы данных в C/C++"
  },
  {
    "subject": "algorithms",
    "question": "Какой тип обычно получит переменная result?\n\nshort a = 10;\nshort b = 20;\nauto result = a + b;",
    "options": {
      "A": "int",
      "B": "short",
      "C": "long",
      "D": "unsigned short",
      "E": "Тип зависит от значения результата"
    },
    "correctAnswers": [
      "A"
    ],
    "explanation": "Перед арифметической операцией значения short проходят целочисленное продвижение и обычно преобразуются в int.",
    "author": "Рабат",
    "topic": "День 2 — Типы данных в C/C++"
  },
  {
    "subject": "algorithms",
    "question": "Какие типы обычно проходят целочисленное продвижение до int в арифметических выражениях?",
    "options": {
      "A": "bool",
      "B": "char",
      "C": "short",
      "D": "double",
      "E": "long long"
    },
    "correctAnswers": [
      "A",
      "B",
      "C"
    ],
    "explanation": "bool, char и short относятся к малым целочисленным типам и перед большинством арифметических операций продвигаются до int, если int может представить их значения.",
    "author": "Рабат",
    "topic": "День 2 — Типы данных в C/C++"
  },
  {
    "subject": "algorithms",
    "question": "Какой тип будет у result?\n\nint a = 5;\ndouble b = 2.5;\nauto result = a + b;",
    "options": {
      "A": "double",
      "B": "int",
      "C": "float",
      "D": "long double",
      "E": "Тип зависит от результата сложения"
    },
    "correctAnswers": [
      "A"
    ],
    "explanation": "Перед сложением int преобразуется в double. Результат арифметической операции также имеет тип double.",
    "author": "Рабат",
    "topic": "День 2 — Типы данных в C/C++"
  },
  {
    "subject": "algorithms",
    "question": "Что произойдёт при переполнении unsigned int?",
    "options": {
      "A": "Значение вычисляется по модулю 2^n",
      "B": "Всегда возникает исключение",
      "C": "Поведение не определено",
      "D": "Программа обязательно завершается",
      "E": "Тип автоматически расширяется"
    },
    "correctAnswers": [
      "A"
    ],
    "explanation": "Беззнаковая арифметика в C++ определена по модулю 2^n, где n — количество битов значения данного типа.",
    "author": "Рабат",
    "topic": "День 2 — Типы данных в C/C++"
  },
  {
    "subject": "algorithms",
    "question": "Какой результат даст код?\n\nunsigned int x = 0;\n--x;",
    "options": {
      "A": "UINT_MAX",
      "B": "-1",
      "C": "0",
      "D": "Ошибка компиляции",
      "E": "Неопределённое поведение"
    },
    "correctAnswers": [
      "A"
    ],
    "explanation": "Беззнаковое значение вычисляется по модулю. При уменьшении нуля на единицу получается максимальное значение unsigned int.",
    "author": "Рабат",
    "topic": "День 2 — Типы данных в C/C++"
  },
  {
    "subject": "algorithms",
    "question": "Что происходит при переполнении signed int?",
    "options": {
      "A": "Возникает неопределённое поведение",
      "B": "Значение гарантированно становится INT_MIN",
      "C": "Значение вычисляется по модулю 2^n",
      "D": "Тип автоматически превращается в long long",
      "E": "Всегда выбрасывается исключение overflow_error"
    },
    "correctAnswers": [
      "A"
    ],
    "explanation": "Переполнение знакового целого типа в C++ является неопределённым поведением. Нельзя полагаться на циклический переход от INT_MAX к INT_MIN.",
    "author": "Рабат",
    "topic": "День 2 — Типы данных в C/C++"
  },
  {
    "subject": "algorithms",
    "question": "Почему следующий код может дать неправильный результат?\n\nint a = 100000;\nint b = 100000;\nlong long result = a * b;",
    "options": {
      "A": "Умножение выполняется как int до присваивания в long long",
      "B": "long long не может хранить результат",
      "C": "Оператор * не работает с int",
      "D": "Компилятор преобразует result в short",
      "E": "100000 является типом float"
    },
    "correctAnswers": [
      "A"
    ],
    "explanation": "Тип выражения определяется по операндам. Оба операнда имеют тип int, поэтому переполнение может произойти до преобразования результата в long long.",
    "author": "Рабат",
    "topic": "День 2 — Типы данных в C/C++"
  },
  {
    "subject": "algorithms",
    "question": "Какие варианты безопасно заставляют умножение выполняться как long long?\n\nint a = 100000;\nint b = 100000;",
    "options": {
      "A": "long long result = 1LL * a * b;",
      "B": "long long result = static_cast<long long>(a) * b;",
      "C": "long long result = a * b;",
      "D": "long long result = static_cast<long long>(a * b);",
      "E": "long long result = (a * b) + 0LL;"
    },
    "correctAnswers": [
      "A",
      "B"
    ],
    "explanation": "В A и B один операнд становится long long до умножения. В C, D и E потенциальное переполнение int происходит раньше последующего преобразования.",
    "author": "Рабат",
    "topic": "День 2 — Типы данных в C/C++"
  },
  {
    "subject": "algorithms",
    "question": "Какое значение обычно получит x для 32-битного unsigned int?\n\nunsigned int x = -5;",
    "options": {
      "A": "4294967291",
      "B": "-5",
      "C": "5",
      "D": "0",
      "E": "Ошибка компиляции"
    },
    "correctAnswers": [
      "A"
    ],
    "explanation": "Отрицательное число преобразуется к беззнаковому по модулю 2^32. Получается 2^32 - 5 = 4294967291.",
    "author": "Рабат",
    "topic": "День 2 — Типы данных в C/C++"
  },
  {
    "subject": "algorithms",
    "question": "Какой результат обычно выведет код при 32-битных int и unsigned int?\n\nint x = -1;\nunsigned int y = 1;\nstd::cout << (x < y);",
    "options": {
      "A": "0",
      "B": "1",
      "C": "-1",
      "D": "Ошибка компиляции",
      "E": "Всегда возникает исключение"
    },
    "correctAnswers": [
      "A"
    ],
    "explanation": "При сравнении x преобразуется в unsigned int. Значение -1 становится UINT_MAX, поэтому сравнение UINT_MAX < 1 ложно.",
    "author": "Рабат",
    "topic": "День 2 — Типы данных в C/C++"
  },
  {
    "subject": "algorithms",
    "question": "Почему следующий цикл является ошибочным?\n\nfor (unsigned int i = 10; i >= 0; --i) {\n    std::cout << i;\n}",
    "options": {
      "A": "Условие i >= 0 всегда истинно для unsigned",
      "B": "unsigned нельзя уменьшать",
      "C": "Цикл выполнится только один раз",
      "D": "Переменная i автоматически становится signed",
      "E": "Оператор >= запрещён для unsigned"
    },
    "correctAnswers": [
      "A"
    ],
    "explanation": "Беззнаковое значение никогда не бывает меньше нуля. После уменьшения нуля i переходит к UINT_MAX, поэтому цикл не завершается.",
    "author": "Рабат",
    "topic": "День 2 — Типы данных в C/C++"
  },
  {
    "subject": "algorithms",
    "question": "Какой результат имеют выражения в C++?\n\n-7 / 3\n-7 % 3",
    "options": {
      "A": "-2 и -1",
      "B": "-3 и 2",
      "C": "2 и -1",
      "D": "-2 и 1",
      "E": "Результат не определён"
    },
    "correctAnswers": [
      "A"
    ],
    "explanation": "Целочисленное деление усекается по направлению к нулю: -7 / 3 равно -2. Остаток удовлетворяет равенству a = (a / b) * b + a % b, поэтому остаток равен -1.",
    "author": "Рабат",
    "topic": "День 2 — Типы данных в C/C++"
  },
  {
    "subject": "algorithms",
    "question": "Что возвращает std::numeric_limits<double>::min()?",
    "options": {
      "A": "Минимальное положительное нормализованное значение",
      "B": "Самое отрицательное конечное значение",
      "C": "Ноль",
      "D": "Отрицательную бесконечность",
      "E": "Самое маленькое по модулю отрицательное число"
    },
    "correctAnswers": [
      "A"
    ],
    "explanation": "Для вещественных типов min() означает минимальное положительное нормализованное значение. Самое отрицательное конечное значение возвращает lowest().",
    "author": "Рабат",
    "topic": "День 2 — Типы данных в C/C++"
  },
  {
    "subject": "algorithms",
    "question": "Как получить самое отрицательное конечное значение типа double?",
    "options": {
      "A": "std::numeric_limits<double>::lowest()",
      "B": "std::numeric_limits<double>::min()",
      "C": "std::numeric_limits<double>::max()",
      "D": "sizeof(double)",
      "E": "DBL_MIN без знака"
    },
    "correctAnswers": [
      "A"
    ],
    "explanation": "lowest() возвращает наименьшее конечное значение, то есть число с наибольшим отрицательным модулем. min() возвращает минимальное положительное нормализованное значение.",
    "author": "Рабат",
    "topic": "День 2 — Типы данных в C/C++"
  },
  {
    "subject": "algorithms",
    "question": "Какие типы из заголовка <cstdint> предназначены для хранения целых чисел фиксированной ширины?",
    "options": {
      "A": "std::int32_t",
      "B": "std::uint64_t",
      "C": "std::int16_t",
      "D": "std::float32_t во всех версиях C++",
      "E": "std::string"
    },
    "correctAnswers": [
      "A",
      "B",
      "C"
    ],
    "explanation": "Типы int32_t, uint64_t и int16_t имеют фиксированную ширину при наличии поддержки платформой. std::string не является числовым типом.",
    "author": "Рабат",
    "topic": "День 2 — Типы данных в C/C++"
  },
  {
    "subject": "algorithms",
    "question": "Какой тип возвращает оператор sizeof?",
    "options": {
      "A": "std::size_t",
      "B": "int",
      "C": "unsigned int во всех реализациях",
      "D": "long long",
      "E": "void"
    },
    "correctAnswers": [
      "A"
    ],
    "explanation": "Результат sizeof имеет тип std::size_t — беззнаковый целочисленный тип, способный представлять размер любого объекта.",
    "author": "Рабат",
    "topic": "День 2 — Типы данных в C/C++"
  },
  {
    "subject": "algorithms",
    "question": "Какие типы выведет компилятор для переменных?\n\nauto a = 10;\nauto b = 10u;\nauto c = 10LL;\nauto d = 3.14f;",
    "options": {
      "A": "int, unsigned int, long long, float",
      "B": "int, int, long, double",
      "C": "long, unsigned long, long long, double",
      "D": "short, unsigned short, long, float",
      "E": "Все переменные получат один тип auto"
    },
    "correctAnswers": [
      "A"
    ],
    "explanation": "10 имеет тип int, 10u — unsigned int, 10LL — long long, а 3.14f — float. auto выводит конкретный статический тип во время компиляции.",
    "author": "Рабат",
    "topic": "День 2 — Типы данных в C/C++"
  },
  {
    "subject": "algorithms",
    "question": "Что произойдёт в коде?\n\nauto x = 10;\nx = 3.9;\nstd::cout << x;",
    "options": {
      "A": "Будет выведено 3",
      "B": "Будет выведено 3.9",
      "C": "Тип x изменится с int на double",
      "D": "Возникнет ошибка компиляции",
      "E": "Будет выведено 4"
    },
    "correctAnswers": [
      "A"
    ],
    "explanation": "auto определяет тип только при объявлении. x получает тип int и не меняет его. При присваивании 3.9 дробная часть отбрасывается.",
    "author": "Рабат",
    "topic": "День 2 — Типы данных в C/C++"
  },
  {
    "subject": "algorithms",
    "question": "Какое значение имеет литерал 010 в C++?",
    "options": {
      "A": "8",
      "B": "10",
      "C": "2",
      "D": "16",
      "E": "Недопустимый литерал"
    },
    "correctAnswers": [
      "A"
    ],
    "explanation": "Целочисленный литерал с ведущим нулём интерпретируется как восьмеричный. Восьмеричное 10 равно десятичному 8.",
    "author": "Рабат",
    "topic": "День 2 — Типы данных в C/C++"
  },
  {
    "subject": "algorithms",
    "question": "Какие литералы представляют десятичное число 42?",
    "options": {
      "A": "42",
      "B": "052",
      "C": "0x2A",
      "D": "0b101010",
      "E": "0x42"
    },
    "correctAnswers": [
      "A",
      "B",
      "C",
      "D"
    ],
    "explanation": "42 — десятичная запись, 052 — восьмеричная, 0x2A — шестнадцатеричная, 0b101010 — двоичная. 0x42 равно десятичному 66.",
    "author": "Рабат",
    "topic": "День 2 — Типы данных в C/C++"
  },
  {
    "subject": "algorithms",
    "question": "Какое утверждение о преобразовании большого целого числа в float является правильным?",
    "options": {
      "A": "Значение может потерять точность, даже если не произошло переполнение",
      "B": "Все значения int всегда точно представимы в float",
      "C": "Преобразование всегда вызывает ошибку компиляции",
      "D": "float автоматически становится double",
      "E": "Большое целое всегда преобразуется в бесконечность"
    },
    "correctAnswers": [
      "A"
    ],
    "explanation": "Диапазон float достаточно большой, но точность ограничена. Поэтому большое целое число может округлиться до ближайшего представимого значения.",
    "author": "Рабат",
    "topic": "День 2 — Типы данных в C/C++"
  }
]

